trick/assemble.py
trick/compile.py
trick/env.py
trick/exceptions.py
trick/fasl.py
trick/features.py
trick/importsets.py
trick/libloader.py
trick/libname.py
trick/library.py
trick/machinetypes.py
trick/primcalls.py
trick/print.py
trick/program.py
trick/qq.py
trick/read.py
trick/repl.py
trick/runtime.py
trick/secd.py
trick/serialization.py
trick/snippet.py
trick/symbolinfo.py
trick/transform.py
trick/trick.py
trick/utils.py
trick/version.py
trick_scheme-0.1.0.dist-info/LICENSE
trick_scheme-0.1.0.dist-info/METADATA
trick_scheme-0.1.0.dist-info/NOTICES
trick_scheme-0.1.0.dist-info/WHEEL
trick_scheme-0.1.0.dist-info/top_level.txt
trick_scheme-0.1.0.dist-info/RECORD
