Metadata-Version: 2.1
Name: trick-scheme
Version: 0.1.0
Summary: An r7rs-small compliant implementation of Scheme
Author-email: Mostafa Razavi <mostafa@sepent.com>
Project-URL: Homepage, https://sr.ht/~elektito/trick
Classifier: Programming Language :: Python :: 3
Classifier: License :: OSI Approved :: GNU General Public License v2 (GPLv2)
Classifier: Operating System :: OS Independent
Requires-Python: >=3.9
License-File: LICENSE
License-File: NOTICES
